amqp_helper/__init__.py
amqp_helper/_amqpclient.py
amqp_helper/_amqpconfig.py
amqp_helper/_amqpfunction.py
amqp_helper/_amqploghandler.py
amqp_helper/_amqpservice.py
amqp_helper/_version.py
amqp_helper-0.1.7.dist-info/LICENSE
amqp_helper-0.1.7.dist-info/METADATA
amqp_helper-0.1.7.dist-info/WHEEL
amqp_helper-0.1.7.dist-info/top_level.txt
amqp_helper-0.1.7.dist-info/RECORD
