Metadata-Version: 2.1
Name: amqp_helper
Version: 0.1.7
Summary: simple Helper library to configure AMQP communication
Home-page: https://github.com/bad-microservices/amqp_helper
Author: Ole Hannemann
Author-email: cerberus885@gmail.com
License: MIT
Keywords: amqp
Classifier: Programming Language :: Python :: 3.0
Classifier: Programming Language :: Python :: 3.9
Classifier: License :: OSI Approved :: MIT License
Classifier: Development Status :: 3 - Alpha
Classifier: Topic :: Software Development :: Libraries :: Python Modules
Classifier: Intended Audience :: Developers
License-File: LICENSE
Requires-Dist: setuptools >=45.0
Requires-Dist: aio-pika >=9.0.0
